<odoo>
    <data noupdate="0">
        <record model="ir.sequence" id="sis_pps_header_ati1_seq">
            <field name="name">Production Planning System Sequence ATI1</field>
            <field name="code">sis.pps.header.ati1.seq</field>
            <field name="active">TRUE</field>
            <field name="prefix">ATI1/%(y)s%(month)s/</field>
            <field name="number_increment">1</field>
            <field name="padding">4</field>
            <field name="implementation">standard</field>
        </record>
        <record model="ir.sequence" id="sis_pps_header_ati2_seq">
            <field name="name">Production Planning System Sequence ATI2</field>
            <field name="code">sis.pps.header.ati2.seq</field>
            <field name="active">TRUE</field>
            <field name="prefix">ATI2/%(y)s%(month)s/</field>
            <field name="number_increment">1</field>
            <field name="padding">4</field>
            <field name="implementation">standard</field>
        </record>

    </data>
</odoo>